{"waypoint_1": {"name": "Kitchen", "pose": {"position": [-3.7786247730255127, -2.414886236190796, 0], "orientation": [0, 0, 0.9999786001338603, 0.0065421154319592325]}, "images": {"0": {"name": "/home/hello-robot/yolov7/images_result/waypoint1/14_54_55_img_5.png", "time": "14_54_55", "objects": ["bowl", "oven", "toaster"], "confidences": ["0.30", "0.40", "0.63"]}, "1": {"name": "/home/hello-robot/yolov7/images_result/waypoint1/14_54_59_img_6.png", "time": "14_54_59", "objects": ["chair", "laptop", "mouse", "oven", "sink", "sink"], "confidences": ["0.27", "0.29", "0.31", "0.47", "0.68", "0.68"]}, "2": {"name": "/home/hello-robot/yolov7/images_result/waypoint1/14_55_02_img_7.png", "time": "14_55_02", "objects": ["oven", "sink", "sink"], "confidences": ["0.34", "0.57", "0.67"]}, "3": {"name": "/home/hello-robot/yolov7/images_result/waypoint1/14_55_06_img_8.png", "time": "14_55_06", "objects": ["bowl", "bowl", "mouse", "keyboard"], "confidences": ["0.27", "0.33", "0.34", "0.61"]}, "4": {"name": "/home/hello-robot/yolov7/images_result/waypoint1/14_55_10_img_9.png", "time": "14_55_10", "objects": ["book"], "confidences": ["0.82"]}}}, "waypoint_2": {"name": "Kitchen", "pose": {"position": [-3.591975212097168, -1.040771484375, 0], "orientation": [0, 0, 0.7094075846424854, 0.704798466834112]}, "images": {"0": {"name": "/home/hello-robot/yolov7/images_result/waypoint2/14_55_48_img_5.png", "time": "14_55_48", "objects": ["bowl", "laptop", "microwave", "microwave", "oven"], "confidences": ["0.34", "0.41", "0.83", "0.87", "0.91"]}, "1": {"name": "/home/hello-robot/yolov7/images_result/waypoint2/14_55_52_img_6.png", "time": "14_55_52", "objects": ["microwave", "oven"], "confidences": ["0.91", "0.94"]}, "2": {"name": "/home/hello-robot/yolov7/images_result/waypoint2/14_55_55_img_7.png", "time": "14_55_55", "objects": ["handbag", "oven", "oven", "toaster"], "confidences": ["0.25", "0.33", "0.36", "0.83"]}, "3": {"name": "/home/hello-robot/yolov7/images_result/waypoint2/14_56_00_img_8.png", "time": "14_56_00", "objects": ["oven"], "confidences": ["0.76"]}, "4": {"name": "/home/hello-robot/yolov7/images_result/waypoint2/14_56_03_img_9.png", "time": "14_56_03", "objects": ["oven"], "confidences": ["0.88"]}}}, "waypoint_3": {"name": "Kitchen", "pose": {"position": [-2.9943723678588867, -2.2064530849456787, 0], "orientation": [0, 0, -0.7143176001199206, 0.6998216673974286]}, "images": {"0": {"name": "/home/hello-robot/yolov7/images_result/waypoint3/14_56_52_img_5.png", "time": "14_56_52", "objects": ["chair", "potted plant", "dining table", "tv", "laptop"], "confidences": ["0.28", "0.30", "0.59", "0.60", "0.70"]}, "1": {"name": "/home/hello-robot/yolov7/images_result/waypoint3/14_56_56_img_6.png", "time": "14_56_56", "objects": ["chair", "potted plant", "dining table", "tv", "laptop"], "confidences": ["0.28", "0.30", "0.59", "0.60", "0.70"]}, "2": {"name": "/home/hello-robot/yolov7/images_result/waypoint3/14_57_00_img_7.png", "time": "14_57_00", "objects": ["chair", "potted plant", "dining table", "tv", "laptop"], "confidences": ["0.28", "0.30", "0.59", "0.60", "0.70"]}, "3": {"name": "/home/hello-robot/yolov7/images_result/waypoint3/14_57_04_img_8.png", "time": "14_57_04", "objects": ["chair", "potted plant", "dining table", "tv", "laptop"], "confidences": ["0.28", "0.30", "0.59", "0.60", "0.70"]}, "4": {"name": "/home/hello-robot/yolov7/images_result/waypoint3/14_57_08_img_9.png", "time": "14_57_08", "objects": ["chair", "potted plant", "dining table", "tv", "laptop"], "confidences": ["0.28", "0.30", "0.59", "0.60", "0.70"]}}}, "waypoint_4": {"name": "Living Room", "pose": {"position": [-0.9331660270690918, -3.810365676879883, 0], "orientation": [0, 0, 0.9999926004613064, 0.003846949783123918]}, "images": {"0": {"name": "/home/hello-robot/yolov7/images_result/waypoint4/14_57_47_img_5.png", "time": "14_57_47", "objects": ["chair", "chair", "chair", "potted plant", "dining table", "mouse", "clock"], "confidences": ["0.36", "0.58", "0.66", "0.79", "0.84", "0.87", "0.91"]}, "1": {"name": "/home/hello-robot/yolov7/images_result/waypoint4/14_57_51_img_6.png", "time": "14_57_51", "objects": ["person", "chair", "chair", "chair", "chair", "potted plant", "tv", "laptop", "laptop", "mouse", "mouse", "mouse", "mouse", "keyboard", "cell phone", "oven", "book"], "confidences": ["0.25", "0.29", "0.34", "0.42", "0.44", "0.44", "0.46", "0.50", "0.53", "0.58", "0.74", "0.76", "0.78", "0.79", "0.86", "0.94", "0.95"]}, "2": {"name": "/home/hello-robot/yolov7/images_result/waypoint4/14_57_54_img_7.png", "time": "14_57_54", "objects": ["dog", "backpack", "cup", "chair", "tv", "microwave", "oven", "oven"], "confidences": ["0.28", "0.32", "0.35", "0.45", "0.58", "0.75", "0.89", "0.90"]}, "3": {"name": "/home/hello-robot/yolov7/images_result/waypoint4/14_57_58_img_8.png", "time": "14_57_58", "objects": ["person", "bench", "chair", "laptop", "laptop", "mouse", "keyboard", "book"], "confidences": ["0.32", "0.33", "0.49", "0.65", "0.81", "0.87", "0.94", "0.95"]}, "4": {"name": "/home/hello-robot/yolov7/images_result/waypoint4/14_58_02_img_9.png", "time": "14_58_02", "objects": ["person", "chair", "chair", "tv", "laptop", "mouse", "mouse", "mouse", "mouse", "keyboard", "book"], "confidences": ["0.25", "0.29", "0.41", "0.43", "0.45", "0.49", "0.54", "0.67", "0.86", "0.94", "0.95"]}}}, "waypoint_5": {"name": "Living Room", "pose": {"position": [-0.6958990097045898, -4.002538681030273, 0], "orientation": [0, 0, 0.013083605250497935, 0.9999144059736559]}, "images": {"0": {"name": "/home/hello-robot/yolov7/images_result/waypoint5/14_58_30_img_5.png", "time": "14_58_30", "objects": ["chair", "couch", "dining table", "tv"], "confidences": ["0.27", "0.31", "0.46", "0.93"]}, "1": {"name": "/home/hello-robot/yolov7/images_result/waypoint5/14_58_34_img_6.png", "time": "14_58_34", "objects": ["person", "cup", "couch", "couch", "potted plant", "potted plant", "potted plant", "dining table", "laptop", "remote"], "confidences": ["0.29", "0.33", "0.33", "0.63", "0.73", "0.73", "0.82", "0.88", "0.91", "0.94"]}, "2": {"name": "/home/hello-robot/yolov7/images_result/waypoint5/14_58_37_img_7.png", "time": "14_58_37", "objects": [], "confidences": []}, "3": {"name": "/home/hello-robot/yolov7/images_result/waypoint5/14_58_41_img_8.png", "time": "14_58_41", "objects": ["sink"], "confidences": ["0.30"]}, "4": {"name": "/home/hello-robot/yolov7/images_result/waypoint5/14_58_45_img_9.png", "time": "14_58_45", "objects": ["person", "person", "cup", "bowl", "couch", "couch", "potted plant", "dining table", "laptop"], "confidences": ["0.28", "0.31", "0.33", "0.36", "0.37", "0.52", "0.86", "0.92", "0.93"]}}}, "waypoint_6": {"name": "Living Room", "pose": {"position": [0.5702148675918579, -0.45569533109664917, 0], "orientation": [0, 0, 0.003317531399193913, 0.999994496977566]}, "images": {"0": {"name": "/home/hello-robot/yolov7/images_result/waypoint6/14_59_29_img_5.png", "time": "14_59_29", "objects": ["tv", "remote", "book"], "confidences": ["0.62", "0.74", "0.85"]}, "1": {"name": "/home/hello-robot/yolov7/images_result/waypoint6/14_59_32_img_6.png", "time": "14_59_32", "objects": ["couch", "potted plant", "potted plant", "dining table", "tv"], "confidences": ["0.25", "0.45", "0.78", "0.78", "0.81"]}, "2": {"name": "/home/hello-robot/yolov7/images_result/waypoint6/14_59_36_img_7.png", "time": "14_59_36", "objects": ["chair", "couch", "potted plant", "book"], "confidences": ["0.34", "0.57", "0.67", "0.79"]}, "3": {"name": "/home/hello-robot/yolov7/images_result/waypoint6/14_59_40_img_8.png", "time": "14_59_40", "objects": ["remote", "book"], "confidences": ["0.37", "0.78"]}, "4": {"name": "/home/hello-robot/yolov7/images_result/waypoint6/14_59_44_img_9.png", "time": "14_59_44", "objects": ["chair"], "confidences": ["0.28"]}}}, "waypoint_7": {"name": "Living Room", "pose": {"position": [2.089517593383789, -1.3541762828826904, 0], "orientation": [0, 0, -0.7022324297955755, 0.7119477611056881]}, "images": {"0": {"name": "/home/hello-robot/yolov7/images_result/waypoint7/15_00_23_img_5.png", "time": "15_00_23", "objects": ["person", "cup", "bowl", "couch", "dining table", "laptop", "book"], "confidences": ["0.26", "0.42", "0.51", "0.67", "0.83", "0.91", "0.92"]}, "1": {"name": "/home/hello-robot/yolov7/images_result/waypoint7/15_00_27_img_6.png", "time": "15_00_27", "objects": ["person", "chair", "chair", "chair", "chair", "chair", "couch", "potted plant", "dining table", "laptop", "remote", "clock"], "confidences": ["0.26", "0.30", "0.31", "0.39", "0.62", "0.65", "0.73", "0.73", "0.74", "0.78", "0.85", "0.95"]}, "2": {"name": "/home/hello-robot/yolov7/images_result/waypoint7/15_00_30_img_7.png", "time": "15_00_30", "objects": ["couch"], "confidences": ["0.93"]}, "3": {"name": "/home/hello-robot/yolov7/images_result/waypoint7/15_00_34_img_8.png", "time": "15_00_34", "objects": ["person", "cup", "bowl", "bowl", "couch", "dining table", "laptop", "remote", "book"], "confidences": ["0.34", "0.36", "0.48", "0.48", "0.51", "0.63", "0.78", "0.91", "0.92"]}, "4": {"name": "/home/hello-robot/yolov7/images_result/waypoint7/15_00_39_img_9.png", "time": "15_00_39", "objects": ["cup", "chair", "chair", "dining table", "tv", "laptop"], "confidences": ["0.31", "0.32", "0.40", "0.56", "0.57", "0.70"]}}}, "waypoint_8": {"name": "Laundry room", "pose": {"position": [-0.49193263053894043, 2.8501291275024414, 0], "orientation": [0, 0, -0.006288086534414319, 0.9999802297884373]}, "images": {"0": {"name": "/home/hello-robot/yolov7/images_result/waypoint8/15_01_31_img_5.png", "time": "15_01_31", "objects": ["backpack", "handbag", "bottle", "bottle", "chair", "refrigerator"], "confidences": ["0.44", "0.47", "0.60", "0.63", "0.68", "0.95"]}, "1": {"name": "/home/hello-robot/yolov7/images_result/waypoint8/15_01_35_img_6.png", "time": "15_01_35", "objects": ["dog", "chair", "bed", "bed"], "confidences": ["0.26", "0.37", "0.38", "0.55"]}, "2": {"name": "/home/hello-robot/yolov7/images_result/waypoint8/15_01_38_img_7.png", "time": "15_01_38", "objects": ["cat", "chair", "refrigerator"], "confidences": ["0.25", "0.54", "0.66"]}, "3": {"name": "/home/hello-robot/yolov7/images_result/waypoint8/15_01_42_img_8.png", "time": "15_01_42", "objects": ["backpack", "bottle", "bowl", "chair"], "confidences": ["0.26", "0.28", "0.37", "0.87"]}, "4": {"name": "/home/hello-robot/yolov7/images_result/waypoint8/15_01_46_img_9.png", "time": "15_01_46", "objects": ["refrigerator"], "confidences": ["0.31"]}}}, "waypoint_9": {"name": "Office", "pose": {"position": [-1.2036025524139404, 3.0047807693481445, 0], "orientation": [0, 0, -0.9954032787583883, 0.09577219135558242]}, "images": {"0": {"name": "/home/hello-robot/yolov7/images_result/waypoint9/15_02_18_img_5.png", "time": "15_02_18", "objects": ["chair", "chair", "tv", "tv", "tv", "keyboard", "keyboard"], "confidences": ["0.26", "0.31", "0.37", "0.41", "0.55", "0.81", "0.96"]}, "1": {"name": "/home/hello-robot/yolov7/images_result/waypoint9/15_02_21_img_6.png", "time": "15_02_21", "objects": [], "confidences": []}, "2": {"name": "/home/hello-robot/yolov7/images_result/waypoint9/15_02_25_img_7.png", "time": "15_02_25", "objects": [], "confidences": []}, "3": {"name": "/home/hello-robot/yolov7/images_result/waypoint9/15_02_29_img_8.png", "time": "15_02_29", "objects": ["chair", "book"], "confidences": ["0.36", "0.95"]}, "4": {"name": "/home/hello-robot/yolov7/images_result/waypoint9/15_02_32_img_9.png", "time": "15_02_32", "objects": ["chair", "refrigerator"], "confidences": ["0.38", "0.39"]}}}, "waypoint_10": {"name": "Bathroom", "pose": {"position": [-1.4174727201461792, 5.705358982086182, 0], "orientation": [0, 0, -0.9965341615267547, 0.0831845232610492]}, "images": {"0": {"name": "/home/hello-robot/yolov7/images_result/waypoint10/15_03_15_img_5.png", "time": "15_03_15", "objects": ["bottle", "sink"], "confidences": ["0.27", "0.55"]}, "1": {"name": "/home/hello-robot/yolov7/images_result/waypoint10/15_03_19_img_6.png", "time": "15_03_19", "objects": [], "confidences": []}, "2": {"name": "/home/hello-robot/yolov7/images_result/waypoint10/15_03_23_img_7.png", "time": "15_03_23", "objects": [], "confidences": []}, "3": {"name": "/home/hello-robot/yolov7/images_result/waypoint10/15_03_26_img_8.png", "time": "15_03_26", "objects": ["sink"], "confidences": ["0.38"]}, "4": {"name": "/home/hello-robot/yolov7/images_result/waypoint10/15_03_30_img_9.png", "time": "15_03_30", "objects": ["refrigerator"], "confidences": ["0.37"]}}}, "waypoint_11": {"name": "Bedroom 1", "pose": {"position": [-0.7242820262908936, 7.054316520690918, 0], "orientation": [0, 0, 0.007939593336931084, 0.9999684809320962]}, "images": {"0": {"name": "/home/hello-robot/yolov7/images_result/waypoint11/15_04_09_img_5.png", "time": "15_04_09", "objects": ["bench", "bed"], "confidences": ["0.31", "0.58"]}, "1": {"name": "/home/hello-robot/yolov7/images_result/waypoint11/15_04_13_img_6.png", "time": "15_04_13", "objects": [], "confidences": []}, "2": {"name": "/home/hello-robot/yolov7/images_result/waypoint11/15_04_16_img_7.png", "time": "15_04_16", "objects": ["refrigerator"], "confidences": ["0.47"]}, "3": {"name": "/home/hello-robot/yolov7/images_result/waypoint11/15_04_20_img_8.png", "time": "15_04_20", "objects": ["chair", "bed", "dining table", "remote", "remote", "book"], "confidences": ["0.31", "0.34", "0.36", "0.53", "0.62", "0.86"]}, "4": {"name": "/home/hello-robot/yolov7/images_result/waypoint11/15_04_24_img_9.png", "time": "15_04_24", "objects": ["bed"], "confidences": ["0.86"]}}}, "waypoint_12": {"name": "Bedroom 2", "pose": {"position": [-1.6974481344223022, 6.971395969390869, 0], "orientation": [0, 0, -0.9999948555277014, 0.003207634351302413]}, "images": {"0": {"name": "/home/hello-robot/yolov7/images_result/waypoint12/15_04_56_img_5.png", "time": "15_04_56", "objects": ["chair", "cell phone", "book", "book", "book", "book"], "confidences": ["0.43", "0.64", "0.69", "0.72", "0.75", "0.90"]}, "1": {"name": "/home/hello-robot/yolov7/images_result/waypoint12/15_05_00_img_6.png", "time": "15_05_00", "objects": ["bed"], "confidences": ["0.82"]}, "2": {"name": "/home/hello-robot/yolov7/images_result/waypoint12/15_05_03_img_7.png", "time": "15_05_03", "objects": ["bed"], "confidences": ["0.72"]}, "3": {"name": "/home/hello-robot/yolov7/images_result/waypoint12/15_05_07_img_8.png", "time": "15_05_07", "objects": ["chair", "remote", "cell phone", "book", "book", "book", "book", "book"], "confidences": ["0.28", "0.29", "0.52", "0.64", "0.68", "0.71", "0.89", "0.90"]}, "4": {"name": "/home/hello-robot/yolov7/images_result/waypoint12/15_05_11_img_9.png", "time": "15_05_11", "objects": [], "confidences": []}}}}